autox/__init__.py
autox/autox.py
autoxtest-0.1.0.dist-info/LICENSE
autoxtest-0.1.0.dist-info/METADATA
autoxtest-0.1.0.dist-info/WHEEL
autoxtest-0.1.0.dist-info/top_level.txt
autoxtest-0.1.0.dist-info/RECORD
