Metadata-Version: 2.1
Name: autoxtest
Version: 0.1.0
Summary: automl for competition
Home-page: https://github.com/4paradigm/autox
Author: caihengxing
Author-email: caihengxing@4paradigm.com
License: UNKNOWN
Platform: UNKNOWN
Requires-Python: >=3.6
License-File: LICENSE
Requires-Dist: numpy
Requires-Dist: pandas
Requires-Dist: tqdm
